cpu/alu.v
// alu.v

module alu (
    output zero,
    input [63:0] A,
    input [63:0] B,
    input [3:0] alu_op,
    output reg [63:0] result 
);

localparam OP_AND    = 4'b0000;
localparam OP_ORR    = 4'b0001; // Note: A | XZR = A - therefore OR and Bypass alu do the same thing if XZR is read as B
localparam OP_ADD    = 4'b0010;
localparam OP_SUB    = 4'b0110;
localparam OP_CPZ    = 4'b0111; // for CBZ.

always @(*) begin
case (alu_op) 
    OP_AND: result = A & B;
    OP_ORR: result = A | B;
    OP_ADD: result = A+B;
    OP_SUB: result = A-B;
    OP_CPZ: result = B | 64'b0; // compare with B rather than A so we can cmp to a imm or a register rather than just a register
    default: result = 64'b0;
endcase
end

// If result = zero 0=true so ZeroBranch (1) & 1 = 1 so pc mux 
assign zero = (result == 64'b0) ? 1'b1 : 1'b0;

endmodule

sim/iverilog/alu_tb.v
`timescale 100ps / 1ps
module alu_tb;
    // Testbench signals
    reg [63:0] A, B;          // Inputs
    reg [3:0] alu_op;         // ALU operation
    wire [63:0] result;       // Output result
    wire zero;                // Zero flag

    // Instantiate the ALU
    alu uut (
        .A(A),
        .B(B),
        .alu_op(alu_op),
        .result(result),
        .zero(zero)
    );

    // Clock generation (optional for combinational ALU)
    reg clk;
    initial begin
        clk = 0;
        forever #5 clk = ~clk; // 10ns period
    end

    // Test stimulus
    initial begin
        // Initialize inputs
        A = 64'b0;
        B = 64'b0;
        alu_op = 4'b0;

        // Open VCD file for waveform viewing
        $dumpfile("alu_tb.vcd");
        $dumpvars(0, alu_tb);

        // Test cases
        #1; // Wait for initial stabilization
        // Test AND: 0xF0F0 & 0x0F0F = 0x0000
        A = 64'hF0F0; B = 64'h0F0F; alu_op = 4'b0000;
        #1;
        // Test ORR: 0xF0F0 | 0x0F0F = 0xFFFF
        A = 64'hF0F0; B = 64'h0F0F; alu_op = 4'b0001;
        #1;
        // Test ADD: 5 + 3 = 8
        A = 64'd5; B = 64'd3; alu_op = 4'b0010;
        #1;
        // Test ADD: 0 + 0 = 0 (check zero flag)
        A = 64'd0; B = 64'd0; alu_op = 4'b0010;
        #1;
        // Test SUB: 5 - 5 = 0 (check zero flag)
        A = 64'd5; B = 64'd5; alu_op = 4'b0110;
        #1;
        // Test SUB: 3 - 5 = -2
        A = 64'd3; B = 64'd5; alu_op = 4'b0110;
        #1;
        // Test MOV: MOV X0, X1 (A = 42, B = 0, ORR) -> result = 42
        A = 64'd42; B = 64'd0; alu_op = 4'b0001;
        #1;
        // Test MOVZ: MOVZ X0, #1 -> result = 1
        A = 64'd0; B = 64'd1; alu_op = 4'b0001;
        #1;
        // Test invalid op (default case)
        A = 64'd10; B = 64'd20; alu_op = 4'b1111;
        #1;
        // should do A | 0 and return non zero thus not enabling the zero flag from the ALU
        A = 64'd10; B = 64'd0; alu_op = 4'b0111;         
        #1;
        //test CBZ branch works in the alu
        A = 64'd0; B = 64'd0; alu_op = 4'b0111;        
        #1;

        // End simulation
        $display("Test completed");
        $finish;
    end

    // Monitor outputs
    initial begin
        $monitor("Time=%0t A=%h B=%h alu_op=%b result=%h zero=%b",
                 $time, A, B, alu_op, result, zero);
    end
endmodule

alu_tb.vcd
$date
	Fri May 16 09:38:57 2025
$end
$version
	Icarus Verilog
$end
$timescale
	1ps
$end
$scope module alu_tb $end
$var wire 1 ! zero $end
$var wire 64 " result [63:0] $end
$var reg 64 # A [63:0] $end
$var reg 64 $ B [63:0] $end
$var reg 4 % alu_op [3:0] $end
$var reg 1 & clk $end
$scope module uut $end
$var wire 64 ' A [63:0] $end
$var wire 64 ( B [63:0] $end
$var wire 4 ) alu_op [3:0] $end
$var wire 1 ! zero $end
$var parameter 4 * OP_ADD $end
$var parameter 4 + OP_AND $end
$var parameter 4 , OP_CPZ $end
$var parameter 4 - OP_ORR $end
$var parameter 4 . OP_SUB $end
$var reg 64 / result [63:0] $end
$upscope $end
$upscope $end
$enddefinitions $end
$comment Show the parameter values. $end
$dumpall
b110 .
b1 -
b111 ,
b0 +
b10 *
$end
#0
$dumpvars
b0 /
b0 )
b0 (
b0 '
0&
b0 %
b0 $
b0 #
b0 "
1!
$end
#100
b111100001111 $
b111100001111 (
b1111000011110000 #
b1111000011110000 '
#200
0!
b1111111111111111 "
b1111111111111111 /
b1 %
b1 )
#300
b1000 "
b1000 /
b10 %
b10 )
b11 $
b11 (
b101 #
b101 '
#400
1!
b0 "
b0 /
b0 $
b0 (
b0 #
b0 '
#500
b110 %
b110 )
b101 $
b101 (
b101 #
b101 '
1&
#600
0!
b1111111111111111111111111111111111111111111111111111111111111110 "
b1111111111111111111111111111111111111111111111111111111111111110 /
b11 #
b11 '
#700
b101010 "
b101010 /
b1 %
b1 )
b0 $
b0 (
b101010 #
b101010 '
#800
b1 "
b1 /
b1 $
b1 (
b0 #
b0 '
#900
1!
b0 "
b0 /
b1111 %
b1111 )
b10100 $
b10100 (
b1010 #
b1010 '
#1000
0!
b1010 "
b1010 /
b111 %
b111 )
b0 $
b0 (
0&
#1100
1!
b0 "
b0 /
b0 #
b0 '
