params.vh
`ifndef PARAMS_VH
`define PARAMS_VH
localparam CBZ_OP  = 8'b10110100;
localparam MOVZ_OP = 9'b110100101;
localparam CMP_OP  = 11'b11101011001;
localparam SUB_OP  = 9'b110100010;
localparam ADD_OP  = 9'b100100010;
localparam B_OP    = 6'b000101;
`endif

cpu/alu.v
// alu.v
`include "params.vh"
module alu (
  output zero,
  input [63:0] A,
  input [63:0] B,
  input [3:0] alu_op,
  output reg [63:0] result 
);

localparam OP_AND    = 4'b0000;
localparam OP_ORR    = 4'b0001; // Note: A | XZR = A - therefore OR and Bypass alu do the same thing if XZR is read as B
localparam OP_ADD    = 4'b0010;
localparam OP_SUB    = 4'b0110;
localparam OP_CPZ    = 4'b0111; // for CBZ.

always @(*) begin
case (alu_op) 
    OP_AND: result = A & B;
    OP_ORR: result = A | B;
    OP_ADD: result = A+B;
    OP_SUB: result = A-B;
    OP_CPZ: result = B | 64'b0; // compare with B rather than A so we can cmp to a imm or a register rather than just a register
    default: result = 64'b0;
endcase
end

// If result = zero 0=true so ZeroBranch (1) & 1 = 1 so pc mux 
assign zero = (result == 64'b0) ? 1'b1 : 1'b0;

endmodule

cpu/alu_control.v
`include "params.vh"
module alu_control (
    input [31:0] instruction,
    input [1:0] ALUOp, // ALU control will only send a signal when the ALUOp flag is set 
    output reg [3:0] alu_op
);

// decode opcode and send a signal to the alu if ALUOp singal is enabled
always @(*) begin
case (ALUOp)

  2'b01: begin // branch operations 
    if (instruction[31:24] == CBZ_OP) begin // CBZ CBZ <Xt>, <label>
      alu_op = 4'b0111;
    end
  end

  2'b10: begin 
  if (instruction[31:21] == MOVZ_OP) begin //MOVZ MOVZ <Xd>, #<imm>{, LSL #<shift>}
    alu_op = 4'b0001;
  end else if (instruction[31:24] == CMP_OP) begin //CMP CMP <Xn>, <Xm>{, <shift> #<amount>}
    alu_op = 4'b0110;
  end else if (instruction[31:23] == SUB_OP) begin // SUBI <Xd|SP>, <Xn|SP>, #<imm>{, <shift>}
    alu_op = 4'b0110;
  end else if (instruction[31:23] == ADD_OP) begin // ADDI <Xd|SP>, <Xn|SP>, #<imm>{, <shift>}
    alu_op = 4'b0010;
  end
  end
  default: alu_op = 4'b0000;

endcase

end

endmodule

cpu/pad.v
// pad.v
`include "params.vh"

module pad (
  input wire [31:0] instruction,
  output reg [63:0] padded_inst
);

always @(*) begin 
  if (instruction[31:21] == 9'b110100101) begin // MOVZ <Xd>, #<imm>{, LSL #<shift>}
    padded_inst = {48'b0, instruction[20:5]};
  end else if (instruction[31:23] == 9'b110100010) begin // SUBI <Xd|SP>, <Xn|SP>, #<imm>{, <shift>}
    padded_inst = {52'b0, instruction[20:5]};
  end else if (instruction[31:23] == 9'b100100001) begin // ADDI <Xd|SP>, <Xn|SP>, #<imm>{, <shift>}
    padded_inst = {52'b0, instruction[20:5]};
  end else begin
    padded_inst = 64'b0;
  end
end

endmodule

cpu/reg_file.v
// registers.v
module reg_file(
  input clk,
  input reset,
  input wire RegWrite,
  input [4:0] Read_register_1,
  input [4:0] Read_register_2,
  input [4:0] Write_register,
  input [63:0] Write_d,
  input wire UseSP,
  output reg [63:0] Read_data_1,
  output reg [63:0] Read_data_2
);
output reg [63:0] X [31:0]; // 64 bit registers * 32 (X0-X31)

always @(*) begin
  if (Read_register_1 == 5'd31) begin
    if (UseSP)
      Read_data_1 = X[31];   // Use SP if instruction specifies it
    else
      Read_data_1 = 64'b0; // Otherwise, XZR (0)
  end
  else
    Read_data_1 = X[Read_register_1];
end

always @(*) begin
  if (Read_register_2 == 5'd31) begin
    if (UseSP)
      Read_data_2 = X[31];   // Use SP if instruction specifies it
    else
      Read_data_2 = 64'b0; // Otherwise, XZR (0)
  end
  else
    Read_data_2 = X[Read_register_2];
end

// if RegWrite begin
//   case (Write_r)
//   0'b0001:  // X0
//   0'b0010:  // X1
//   0'b0011:  // X2
//   endcase
// end

endmodule

cpu/control.v
// control.v
`include "params.vh"
module control (
  input [31:0] instruction,  

  // Control Bits
  output reg Reg2Loc,
  output reg UncondBranch,
  output reg FlagBranch,
  output reg ZeroBranch,
  output reg MemRead,
  output reg MemToReg,
  output reg MemWrite,
  output reg FlagWrite,
  output reg ALUSrc,
  output reg [1:0] ALUOp, // this is wide not one bit
  output reg RegWrite,
  output reg UseSP
);


// On start
always @(*) begin 

  Reg2Loc = 1'b0;
  UncondBranch = 1'b0;
  FlagBranch = 1'b0;
  ZeroBranch = 1'b0;
  MemRead = 1'b0;
  MemToReg = 1'b0;
  MemWrite = 1'b0;
  FlagWrite = 1'b0;
  ALUSrc = 1'b0;
  ALUOp = 2'b00;
  RegWrite = 1'b0;

  if (instruction[31:24] == CBZ_OP) begin // CBZ CBZ <Xt>, <label>
    Reg2Loc = 1'b1;
    ZeroBranch=1'b1;
    ALUOp = 2'b01;
  end else if (instruction[31:26] == B_OP) begin //B B <label>
    UncondBranch = 1'b1;
  end else if (instruction[31:21] == MOVZ_OP) begin //MOVZ MOVZ <Xd>, #<imm>{, LSL #<shift>}
    RegWrite = 1'b1;
  end else if (instruction[31:21] == CMP_OP) begin //CMP CMP <Xn>, <Xm>{, <shift> #<amount>}
    ALUOp = 2'b01;
  end else if (instruction[31:23] == SUB_OP) begin // SUBI <Xd|SP>, <Xn|SP>, #<imm>{, <shift>}
    ALUOp = 2'b10;
    UseSP = 1'b1;
  end else if (instruction[31:23] == ADD_OP) begin // ADD <Xd|SP>, <Xn|SP>, #<imm>{, <shift>}
    ALUOp = 2'b10;

  end
end

endmodule

cpu/dmem.v
//dmem.v
`include "params.vh"
module dmem (
    input clk,
    input [63:0] address,
    input wire MemWrite,
    input wire MemRead,
    input [63:0] Write_d,
    output reg [63:0] Read_d
);

localparam MEMSIZE = 1024;
reg [63:0] d_mem [0:MEMSIZE-1];

always @(posedge clk) begin
  if (MemWrite) begin
    d_mem[address[11:2]] <= Write_d;
  end
end

always @(*) begin 
  if (MemRead) begin 
    Read_d = d_mem[address[11:2]];
  end else begin
    Read_d = 64'b0;
  end

end
endmodule

cpu/imem.v
// instruction_memory.v
`include "params.vh"
module imem (
input wire [63:0] pc, // reads from PC
output wire [31:0] instruction // reads from memory the instruction 
);
  localparam MEMSIZE = 1024; // 1024 Instructions ~ 1024*4 = 4Kib
  localparam INSTRUCTION_N = 8;
  reg [31:0] i_mem[0:MEMSIZE-1];

initial begin 
    // Using assembly generated by my minimal rust assembler (https://github.com/1957-001B/ArmAsm)

    i_mem[0] = 32'hd2800088;
    i_mem[1] = 32'hd2800020;
    i_mem[2] = 32'h58000081;
    i_mem[3] = 32'hd28001a2;
    i_mem[4] = 32'hd4000001;
    i_mem[5] = 32'hd2800028;
    i_mem[6] = 32'hd2800000;
    i_mem[7] = 32'hd4000001;

    for (integer i = INSTRUCTION_N; i < MEMSIZE; i = i+1) begin
      i_mem[i] = 32'hd540643f;
    end

  end

  assign instruction = i_mem[pc[11:2]]; //right shifted twice to align with the 4 bit instuctions (i.e divide by 4)

endmodule

cpu/cpu.v
// cpu.v
`include "params.vh"
module cpu (
    input clk,
    input reset,
    output reg [63:0] pc,
    output wire halted
  );

// set by the bootloader
localparam INITPC =  64'h0;
localparam INITSP = 1000;

// Wires definitions
// Instruction Memory
wire [31:0] instruction;

// Sign Extend / Pad
wire [63:0] padded_imm;

//Control Unit
wire Reg2Loc;
wire UncondBranch;
wire FlagBranch;
wire ZeroBranch;
wire MemRead;
wire MemToReg;
wire MemWrite;
wire FlagWrite;
wire ALUSrc;
wire [1:0] ALUOp;
wire RegWrite;
wire UseSP;

// Data Memory
wire [63:0] Read_d;

// Register File 
wire [4:0] Read_register_1;
wire [4:0] Read_register_2;
assign Read_register_1 = instruction[9:5];
assign Read_register_2 = Reg2Loc ? instruction[20:16] : instruction[4:0];
wire [4:0] Write_register;
wire [63:0] Write_d;
wire [63:0] alu_result;
assign Write_d = MemToReg ? alu_result : Read_d;
wire [63:0] Read_data_1;
wire [63:0] Read_data_2;

//Alu
wire alu_zero;
wire mod_flags; //not sure if I will input flag branches
wire [63:0] alu_mux;
assign alu_mux = ALUSrc ? Read_data_2 : padded_imm;

// Alu Control
wire [3:0] alu_op;

// Output the current instruction at the PC.
imem instruction_memory(
  .pc(pc),
  .instruction(instruction)
);

dmem data_memory(
  .clk(clk),
  .address(alu_result),
  .MemWrite(MemWrite),
  .MemRead(MemRead),
  .Read_d(Read_d)
);

control control_unit(
  .instruction(instruction),
  .UncondBranch(UncondBranch),
  .FlagBranch(FlagBranch),
  .ZeroBranch(ZeroBranch),
  .MemRead(MemRead),
  .MemToReg(MemToReg),
  .MemWrite(MemWrite),
  .FlagWrite(FlagWrite),
  .ALUSrc(ALUSrc),
  .ALUOp(ALUOp),
  .RegWrite(RegWrite),
  .UseSP(UseSP)
);

reg_file registers( 
  .clk(clk),
  .reset(reset),
  .RegWrite(RegWrite),
  .Read_register_1(Read_register_1),
  .Read_register_2(Read_register_2),
  .Write_register(Write_register),
  .Write_d(Write_d),
  .Read_data_1(Read_data_1),
  .Read_data_2(Read_data_2),
  .UseSP(UseSP)
);

pad pad(
  .instruction(instruction),
  .padded_inst(padded_imm)
);

alu_control aluctrl(
  .instruction(instruction),
  .ALUOp(ALUOp),
  .alu_op(alu_op)
);

alu alu(
  .zero(alu_zero),
  .A(Read_data_1),
  .B(alu_mux),
  .alu_op(alu_op),
  .result(alu_result)
);

//  PC logic
wire [63:0] pc_norm, pc_jump, pc_mux;
wire pc_select;

assign pc_norm = pc + 4;
assign pc_jump = pc + 4;
assign pc_select = UncondBranch | FlagBranch | (ZeroBranch & alu_zero);
assign pc_mux = pc_select ? pc_norm : pc_jump ;


always @(posedge clk or posedge reset) begin
    if (reset) begin
      pc <= INITPC;
      end else if (!halted) begin  
        pc <= pc_mux;
      end
    end 

endmodule

sim/cpu_tb.v
// cpu_tb.v
// example testbed
`timescale 1ns/1ps
module cpu_tb;
    // Inputs to CPU
    reg clk;
    reg reset;
    // Outputs from CPU
    wire [63:0] pc;
    wire [9:0] opcode;
    wire halted;
    assign halted = 0;
    // Instantiate CPU
    cpu uut (
        .clk(clk),
        .reset(reset),
        .pc(pc),
        .halted(halted)
    );

    // Clock generation
    always #5 clk = ~clk; // 100 MHz clock (10ns period)

    // Test stimulus
    initial begin
        // Initialize signals
        clk = 0;
        reset = 1;

        // Dump waveform for debugging
        $dumpfile("wave.vcd");
        $dumpvars(0, cpu_tb);

        // Apply reset
        #10 reset = 0; // Release reset after 20ns

        // Run for a few cycles
        #100;

        // Finish simulation
        $finish;
    end

    // Monitor outputs
    initial
        $monitor("Time=%0t clk=%b reset=%b pc=%h ", $time, clk, reset, pc);
endmodule

wave.vcd
$date
	Tue May 20 15:20:25 2025
$end
$version
	Icarus Verilog
$end
$timescale
	1ps
$end
$scope module cpu_tb $end
$var wire 1 ! halted $end
$var wire 64 " pc [63:0] $end
$var reg 1 # clk $end
$var reg 1 $ reset $end
$scope module uut $end
$var wire 1 % Reg2Loc $end
$var wire 5 & Write_register [4:0] $end
$var wire 1 # clk $end
$var wire 1 ! halted $end
$var wire 1 ' pc_select $end
$var wire 1 $ reset $end
$var wire 64 ( pc_norm [63:0] $end
$var wire 64 ) pc_mux [63:0] $end
$var wire 64 * pc_jump [63:0] $end
$var wire 64 + padded_imm [63:0] $end
$var wire 32 , instruction [31:0] $end
$var wire 1 - alu_zero $end
$var wire 64 . alu_result [63:0] $end
$var wire 4 / alu_op [3:0] $end
$var wire 64 0 alu_mux [63:0] $end
$var wire 1 1 ZeroBranch $end
$var wire 64 2 Write_d [63:0] $end
$var wire 1 3 UseSP $end
$var wire 1 4 UncondBranch $end
$var wire 1 5 RegWrite $end
$var wire 5 6 Read_register_2 [4:0] $end
$var wire 5 7 Read_register_1 [4:0] $end
$var wire 64 8 Read_data_2 [63:0] $end
$var wire 64 9 Read_data_1 [63:0] $end
$var wire 64 : Read_d [63:0] $end
$var wire 1 ; MemWrite $end
$var wire 1 < MemToReg $end
$var wire 1 = MemRead $end
$var wire 1 > FlagWrite $end
$var wire 1 ? FlagBranch $end
$var wire 1 @ ALUSrc $end
$var wire 2 A ALUOp [1:0] $end
$var parameter 64 B INITPC $end
$var parameter 32 C INITSP $end
$var reg 64 D pc [63:0] $end
$scope module alu $end
$var wire 64 E B [63:0] $end
$var wire 1 - zero $end
$var wire 4 F alu_op [3:0] $end
$var wire 64 G A [63:0] $end
$var parameter 4 H OP_ADD $end
$var parameter 4 I OP_AND $end
$var parameter 4 J OP_CPZ $end
$var parameter 4 K OP_ORR $end
$var parameter 4 L OP_SUB $end
$var reg 64 M result [63:0] $end
$upscope $end
$scope module aluctrl $end
$var wire 32 N instruction [31:0] $end
$var wire 2 O ALUOp [1:0] $end
$var reg 4 P alu_op [3:0] $end
$upscope $end
$scope module control_unit $end
$var wire 32 Q instruction [31:0] $end
$var reg 2 R ALUOp [1:0] $end
$var reg 1 @ ALUSrc $end
$var reg 1 ? FlagBranch $end
$var reg 1 > FlagWrite $end
$var reg 1 = MemRead $end
$var reg 1 < MemToReg $end
$var reg 1 ; MemWrite $end
$var reg 1 S Reg2Loc $end
$var reg 1 5 RegWrite $end
$var reg 1 4 UncondBranch $end
$var reg 1 3 UseSP $end
$var reg 1 1 ZeroBranch $end
$upscope $end
$scope module data_memory $end
$var wire 1 = MemRead $end
$var wire 1 ; MemWrite $end
$var wire 64 T Write_d [63:0] $end
$var wire 64 U address [63:0] $end
$var wire 1 # clk $end
$var parameter 32 V MEMSIZE $end
$var reg 64 W Read_d [63:0] $end
$upscope $end
$scope module instruction_memory $end
$var wire 32 X instruction [31:0] $end
$var wire 64 Y pc [63:0] $end
$var parameter 32 Z INSTRUCTION_N $end
$var parameter 32 [ MEMSIZE $end
$scope begin $ivl_for_loop0 $end
$var integer 32 \ i [31:0] $end
$upscope $end
$upscope $end
$scope module pad $end
$var wire 32 ] instruction [31:0] $end
$var reg 64 ^ padded_inst [63:0] $end
$upscope $end
$scope module registers $end
$var wire 5 _ Read_register_1 [4:0] $end
$var wire 5 ` Read_register_2 [4:0] $end
$var wire 1 5 RegWrite $end
$var wire 1 3 UseSP $end
$var wire 64 a Write_d [63:0] $end
$var wire 5 b Write_register [4:0] $end
$var wire 1 # clk $end
$var wire 1 $ reset $end
$var reg 64 c Read_data_1 [63:0] $end
$var reg 64 d Read_data_2 [63:0] $end
$upscope $end
$upscope $end
$upscope $end
$enddefinitions $end
$comment Show the parameter values. $end
$dumpall
b10000000000 [
b1000 Z
b10000000000 V
b110 L
b1 K
b111 J
b0 I
b10 H
b1111101000 C
b0 B
$end
#0
$dumpvars
bx d
bx c
bz b
b0 a
b0x000 `
b100 _
b0 ^
b11010010100000000000000010001000 ]
b10000000000 \
b0 Y
b11010010100000000000000010001000 X
b0 W
b0 U
bz T
0S
b0 R
b11010010100000000000000010001000 Q
b0 P
b0 O
b11010010100000000000000010001000 N
b0 M
bx G
b0 F
b0 E
b0 D
b0 A
0@
0?
0>
0=
0<
0;
b0 :
bx 9
bx 8
b100 7
b0x000 6
05
04
x3
b0 2
01
b0 0
b0 /
b0 .
1-
b11010010100000000000000010001000 ,
b0 +
b100 *
b100 )
b100 (
0'
bz &
z%
1$
0#
b0 "
0!
$end
#5000
1#
#10000
0#
0$
#15000
b0 6
b0 `
b1 7
b1 _
b1000 )
b11010010100000000000000000100000 ,
b11010010100000000000000000100000 N
b11010010100000000000000000100000 Q
b11010010100000000000000000100000 X
b11010010100000000000000000100000 ]
b1000 (
b1000 *
b100 "
b100 D
b100 Y
1#
#20000
0#
#25000
b0x 6
b0x `
b100 7
b100 _
b1100 )
b1011000000000000000000010000001 ,
b1011000000000000000000010000001 N
b1011000000000000000000010000001 Q
b1011000000000000000000010000001 X
b1011000000000000000000010000001 ]
b1100 (
b1100 *
b1000 "
b1000 D
b1000 Y
1#
#30000
0#
#35000
b0x0 6
b0x0 `
b1101 7
b1101 _
b10000 )
b11010010100000000000000110100010 ,
b11010010100000000000000110100010 N
b11010010100000000000000110100010 Q
b11010010100000000000000110100010 X
b11010010100000000000000110100010 ]
b10000 (
b10000 *
b1100 "
b1100 D
b1100 Y
1#
#40000
0#
#45000
b0x 6
b0x `
b0 7
b0 _
b10100 )
b11010100000000000000000000000001 ,
b11010100000000000000000000000001 N
b11010100000000000000000000000001 Q
b11010100000000000000000000000001 X
b11010100000000000000000000000001 ]
b10100 (
b10100 *
b10000 "
b10000 D
b10000 Y
1#
#50000
0#
#55000
b0x000 6
b0x000 `
b1 7
b1 _
b11000 )
b11010010100000000000000000101000 ,
b11010010100000000000000000101000 N
b11010010100000000000000000101000 Q
b11010010100000000000000000101000 X
b11010010100000000000000000101000 ]
b11000 (
b11000 *
b10100 "
b10100 D
b10100 Y
1#
#60000
0#
#65000
b0 6
b0 `
b0 7
b0 _
b11100 )
b11010010100000000000000000000000 ,
b11010010100000000000000000000000 N
b11010010100000000000000000000000 Q
b11010010100000000000000000000000 X
b11010010100000000000000000000000 ]
b11100 (
b11100 *
b11000 "
b11000 D
b11000 Y
1#
#70000
0#
#75000
b0x 6
b0x `
b100000 )
b11010100000000000000000000000001 ,
b11010100000000000000000000000001 N
b11010100000000000000000000000001 Q
b11010100000000000000000000000001 X
b11010100000000000000000000000001 ]
b100000 (
b100000 *
b11100 "
b11100 D
b11100 Y
1#
#80000
0#
#85000
bx 6
bx `
b1 7
b1 _
b100100 )
b11010101010000000110010000111111 ,
b11010101010000000110010000111111 N
b11010101010000000110010000111111 Q
b11010101010000000110010000111111 X
b11010101010000000110010000111111 ]
b100100 (
b100100 *
b100000 "
b100000 D
b100000 Y
1#
#90000
0#
#95000
b101000 )
b101000 (
b101000 *
b100100 "
b100100 D
b100100 Y
1#
#100000
0#
#105000
b101100 )
b101100 (
b101100 *
b101000 "
b101000 D
b101000 Y
1#
