cpu.v
// cpu.v
// Minimal Armv8 cpu
// Initially single cycle and then a basic pipeline 

module cpu (
    input clk,
    input reset,

    output reg [63:0] pc,
    output reg [63:0] sp
);

  wire [31:0] instruction;
    // Basic ARMv8 PC incrementer (placeholder)
    always @(posedge clk or posedge reset) begin
        if (reset)
            pc <= 0;
            sp <= 0;
        else
            pc <= pc + 4; // Increment PC by 4 (ARMv8 instruction size)
            sp <= pc + 4; 
    end

    // control_unit control_unit_instance (
    //   // UncondBranch()
    //   // FlagBranch()
    //   // ZeroBranch()
    //   // MemRead()
    //   // MemToReg()
    //   // MemWrite()
    //   // FlagWrite()
    //   // ALUSrc
    //   // ALUOp(alu)
    //   // RegWrite(registers)
    // )

endmodule

cpu_tb.v
// cpu_tb.v
// example testbed
`timescale 1ns/1ps
module cpu_tb;
    // Inputs to CPU
    reg clk;
    reg reset;
    // Outputs from CPU
    wire [63:0] pc;
    wire [63:0] sp;

    // Instantiate CPU
    cpu uut (
        .clk(clk),
        .reset(reset),
        .pc(pc)
    );

    // Clock generation
    always #5 clk = ~clk; // 100 MHz clock (10ns period)

    // Test stimulus
    initial begin
        // Initialize signals
        clk = 0;
        reset = 1;

        // Dump waveform for debugging
        $dumpfile("wave.vcd");
        $dumpvars(0, cpu_tb);

        // Apply reset
        #20 reset = 0; // Release reset after 20ns

        // Run for a few cycles
        #100;

        // Finish simulation
        $finish;
    end

    // Monitor outputs
    initial
        $monitor("Time=%0t clk=%b reset=%b pc=%h sp=%h", $time, clk, reset, pc, sp);
endmodule

wave.vcd
$date
	Wed May 14 13:56:15 2025
$end
$version
	Icarus Verilog
$end
$timescale
	1ps
$end
$scope module cpu_tb $end
$var wire 64 ! sp [63:0] $end
$var wire 64 " pc [63:0] $end
$var reg 1 # clk $end
$var reg 1 $ reset $end
$scope module uut $end
$var wire 1 # clk $end
$var wire 1 $ reset $end
$var reg 64 % pc [63:0] $end
$var reg 64 & sp [63:0] $end
$upscope $end
$upscope $end
$enddefinitions $end
$comment Show the parameter values. $end
$dumpall
$end
#0
$dumpvars
bx &
b0 %
1$
0#
b0 "
bz !
$end
#5000
b100 &
1#
#10000
0#
#15000
1#
#20000
0#
0$
#25000
b100 "
b100 %
1#
#30000
0#
#35000
b1000 &
b1000 "
b1000 %
1#
#40000
0#
#45000
b1100 &
b1100 "
b1100 %
1#
#50000
0#
#55000
b10000 &
b10000 "
b10000 %
1#
#60000
0#
#65000
b10100 &
b10100 "
b10100 %
1#
#70000
0#
#75000
b11000 &
b11000 "
b11000 %
1#
#80000
0#
#85000
b11100 &
b11100 "
b11100 %
1#
#90000
0#
#95000
b100000 &
b100000 "
b100000 %
1#
#100000
0#
#105000
b100100 &
b100100 "
b100100 %
1#
#110000
0#
#115000
b101000 &
b101000 "
b101000 %
1#
